jsii_publish_test/__init__.py
jsii_publish_test/py.typed
jsii_publish_test/_jsii/__init__.py
jsii_publish_test/_jsii/jsii-publish-test@0.13.1965.jsii.tgz
jsii_publish_test-0.13.1965.dist-info/LICENSE
jsii_publish_test-0.13.1965.dist-info/METADATA
jsii_publish_test-0.13.1965.dist-info/WHEEL
jsii_publish_test-0.13.1965.dist-info/top_level.txt
jsii_publish_test-0.13.1965.dist-info/RECORD
