Metadata-Version: 2.1
Name: jsii-publish-test
Version: 0.13.1965
Summary: A dummy construct, used for automated testing of jsii-publish
Home-page: https://github.com/udondan/jsii-publish
Author: Daniel Schroeder
License: MIT
Project-URL: Source, https://github.com/udondan/jsii-publish.git
Platform: UNKNOWN
Classifier: Intended Audience :: Developers
Classifier: Operating System :: OS Independent
Classifier: Programming Language :: JavaScript
Classifier: Programming Language :: Python :: 3 :: Only
Classifier: Programming Language :: Python :: 3.6
Classifier: Programming Language :: Python :: 3.7
Classifier: Programming Language :: Python :: 3.8
Classifier: Programming Language :: Python :: 3.9
Classifier: Typing :: Typed
Classifier: Development Status :: 4 - Beta
Classifier: License :: OSI Approved
Requires-Python: >=3.6
License-File: LICENSE
Requires-Dist: aws-cdk-lib (<3.0.0,>=2.21.1)
Requires-Dist: jsii (<2.0.0,>=1.57.0)
Requires-Dist: publication (>=0.0.3)
